{
    "data": [
        {
            "cityId": 440300,
            "cityName": "深圳",
            "mappingUrl": "http://www.urlpp.com/f83k"
        },
        {
            "cityId": 440100,
            "cityName": "广州",
            "mappingUrl": "http://www.urlpp.com/f83k"
        },
        {
            "cityId": 310100,
            "cityName": "上海",
            "mappingUrl": "http://www.urlpp.com/f83k"
        },
        {
            "cityId": 110100,
            "cityName": "北京",
            "mappingUrl": "http://www.urlpp.com/f83k"
        },
        {
            "cityId": 120100,
            "cityName": "天津",
            "mappingUrl": "http://www.urlpp.com/f83k"
        },
        {
            "cityId": 500100,
            "cityName": "重庆",
            "mappingUrl": "http://www.urlpp.com/f83k"
        }
    ],
    "meta": {
        "code": "00000",
        "msg": "ok",
        "success": true
    }
}